{
    "AX": {
        "error": 0.009546761593007458,
        "error_type": "SEM",
        "filter_outliers_dict": {
            "filter_outliers": true,
            "iterations": 1,
            "std_devs": 2
        },
        "fit": "average",
        "modifier_error": 0.0,
        "modifier_value": 0.0,
        "value": -0.21639443452236048
    },
    "CDD": {
        "error": 4.565555880127542e-06,
        "error_type": "SEM",
        "filter_outliers_dict": {
            "filter_outliers": true,
            "iterations": 1,
            "std_devs": 10
        },
        "fit": "average",
        "modifier_error": 9.443789951775921e-06,
        "modifier_value": 2.0131470471396657e-05,
        "value": 2.4697026351524205e-05
    },
    "H1": {
        "error": 0.008099200201557768,
        "error_type": "SEM",
        "filter_outliers_dict": {
            "filter_outliers": true,
            "iterations": 1,
            "std_devs": 2
        },
        "fit": "average",
        "modifier_error": 0.0,
        "modifier_value": 0.0,
        "value": 0.053380951625496414
    },
    "H2": {
        "error": 0.0068604461924636215,
        "error_type": "SEM",
        "filter_outliers_dict": {
            "filter_outliers": true,
            "iterations": 1,
            "std_devs": 2
        },
        "fit": "average",
        "modifier_error": 0.0,
        "modifier_value": 0.0,
        "value": 0.050920975130606276
    },
    "L1": {
        "error": 0.003959473431726373,
        "error_type": "SEM",
        "filter_outliers_dict": {
            "filter_outliers": true,
            "iterations": 1,
            "std_devs": 2
        },
        "fit": "average",
        "modifier_error": 0.0,
        "modifier_value": 0.0,
        "value": 0.05257414422183381
    },
    "L2": {
        "error": 0.005209087376580782,
        "error_type": "SEM",
        "filter_outliers_dict": {
            "filter_outliers": true,
            "iterations": 1,
            "std_devs": 2
        },
        "fit": "average",
        "modifier_error": 0.0,
        "modifier_value": 0.0,
        "value": -0.0397168075943811
    }
}