{
    "AX": {
        "error": 0.010544389623292265,
        "error_type": "SEM",
        "filter_outliers_dict": {
            "filter_outliers": true,
            "iterations": 1,
            "std_devs": 3,
            "use_iqr_filtering": false,
            "use_standard_deviation_filtering": false
        },
        "fit": "average",
        "fn": 35,
        "include_baseline_error": false,
        "modifier_error": 0.0,
        "modifier_value": 0.0,
        "n": 35,
        "outlier_excluded": [],
        "reviewed": true,
        "user_excluded": [],
        "value": -0.07884159624310476
    },
    "CDD": {
        "error": 1.1613564843291503e-05,
        "error_type": "SEM",
        "filter_outliers_dict": {
            "filter_outliers": true,
            "iterations": 1,
            "std_devs": 10,
            "use_iqr_filtering": false,
            "use_standard_deviation_filtering": false
        },
        "fit": "average",
        "fn": 35,
        "include_baseline_error": false,
        "modifier_error": 9.550617942788687e-06,
        "modifier_value": 2.05991979647045e-05,
        "n": 35,
        "outlier_excluded": [],
        "reviewed": true,
        "user_excluded": [],
        "value": 4.342697746843831e-05
    },
    "H1": {
        "error": 0.007449758504068634,
        "error_type": "SEM",
        "filter_outliers_dict": {
            "filter_outliers": true,
            "iterations": 1,
            "std_devs": 3,
            "use_iqr_filtering": false,
            "use_standard_deviation_filtering": false
        },
        "fit": "average",
        "fn": 35,
        "include_baseline_error": false,
        "modifier_error": 0.0,
        "modifier_value": 0.0,
        "n": 35,
        "outlier_excluded": [],
        "reviewed": true,
        "user_excluded": [],
        "value": -0.0053492232791281175
    },
    "H2": {
        "error": 0.008163687673929563,
        "error_type": "SEM",
        "filter_outliers_dict": {
            "filter_outliers": true,
            "iterations": 1,
            "std_devs": 3,
            "use_iqr_filtering": false,
            "use_standard_deviation_filtering": false
        },
        "fit": "average",
        "fn": 35,
        "include_baseline_error": false,
        "modifier_error": 0.0,
        "modifier_value": 0.0,
        "n": 35,
        "outlier_excluded": [],
        "reviewed": true,
        "user_excluded": [],
        "value": -0.0011590738448181322
    },
    "L1": {
        "error": 0.005362413679842322,
        "error_type": "SEM",
        "filter_outliers_dict": {
            "filter_outliers": true,
            "iterations": 1,
            "std_devs": 3,
            "use_iqr_filtering": false,
            "use_standard_deviation_filtering": false
        },
        "fit": "average",
        "fn": 35,
        "include_baseline_error": false,
        "modifier_error": 0.0,
        "modifier_value": 0.0,
        "n": 35,
        "outlier_excluded": [],
        "reviewed": true,
        "user_excluded": [],
        "value": 0.031202855471721185
    },
    "L2": {
        "error": 0.004799527751579498,
        "error_type": "SEM",
        "filter_outliers_dict": {
            "filter_outliers": true,
            "iterations": 1,
            "std_devs": 3,
            "use_iqr_filtering": false,
            "use_standard_deviation_filtering": false
        },
        "fit": "average",
        "fn": 35,
        "include_baseline_error": false,
        "modifier_error": 0.0,
        "modifier_value": 0.0,
        "n": 35,
        "outlier_excluded": [],
        "reviewed": true,
        "user_excluded": [],
        "value": -0.03447259900027088
    }
}